pachyderm_sdk/__init__.py
pachyderm_sdk/__main__.py
pachyderm_sdk/api/.gitignore
pachyderm_sdk/api/__init__.py
pachyderm_sdk/api/admin/__init__.py
pachyderm_sdk/api/admin/extension.py
pachyderm_sdk/api/auth/__init__.py
pachyderm_sdk/api/cdr/__init__.py
pachyderm_sdk/api/cdr/resolver.py
pachyderm_sdk/api/debug/__init__.py
pachyderm_sdk/api/debug/extension.py
pachyderm_sdk/api/enterprise/__init__.py
pachyderm_sdk/api/identity/__init__.py
pachyderm_sdk/api/license/__init__.py
pachyderm_sdk/api/logs/__init__.py
pachyderm_sdk/api/metadata/__init__.py
pachyderm_sdk/api/pfs/__init__.py
pachyderm_sdk/api/pfs/_additions.py
pachyderm_sdk/api/pfs/extension.py
pachyderm_sdk/api/pfs/file.py
pachyderm_sdk/api/pjs/__init__.py
pachyderm_sdk/api/pps/__init__.py
pachyderm_sdk/api/pps/_additions.py
pachyderm_sdk/api/pps/extension.py
pachyderm_sdk/api/snapshot/__init__.py
pachyderm_sdk/api/storage/__init__.py
pachyderm_sdk/api/storage/extension.py
pachyderm_sdk/api/taskapi/__init__.py
pachyderm_sdk/api/transaction/__init__.py
pachyderm_sdk/api/transaction/extension.py
pachyderm_sdk/api/version/__init__.py
pachyderm_sdk/api/worker/__init__.py
pachyderm_sdk/api/worker/extension.py
pachyderm_sdk/client.py
pachyderm_sdk/config.py
pachyderm_sdk/constants.py
pachyderm_sdk/datum_batching.py
pachyderm_sdk/errors.py
pachyderm_sdk/interceptor.py
pachyderm_sdk-2.12.2.dist-info/METADATA
pachyderm_sdk-2.12.2.dist-info/WHEEL
pachyderm_sdk-2.12.2.dist-info/entry_points.txt
pachyderm_sdk-2.12.2.dist-info/RECORD
