Metadata-Version: 2.1
Name: pachyderm-sdk
Version: 2.12.2
Summary: Python Pachyderm Client
Home-page: https://github.com/pachyderm/pachyderm/tree/master/python-sdk
License: Apache 2.0
Keywords: pachyderm
Author: Pachyderm Integrations
Author-email: integrations@pachyderm.io
Requires-Python: >=3.9,<4.0
Classifier: Intended Audience :: Developers
Classifier: License :: OSI Approved :: Apache Software License
Classifier: License :: Other/Proprietary License
Classifier: Programming Language :: Python :: 3
Classifier: Programming Language :: Python :: 3.9
Classifier: Programming Language :: Python :: 3.10
Classifier: Programming Language :: Python :: 3.11
Classifier: Programming Language :: Python :: 3
Classifier: Programming Language :: Python :: 3.10
Classifier: Programming Language :: Python :: 3.11
Classifier: Programming Language :: Python :: 3.12
Classifier: Programming Language :: Python :: 3.13
Classifier: Programming Language :: Python :: 3.9
Classifier: Programming Language :: Python :: Implementation :: CPython
Provides-Extra: cdr
Requires-Dist: betterproto (==2.0.0b6)
Requires-Dist: certifi (>=2022.9)
Requires-Dist: grpc-interceptor (>=0.14.2,<0.15.0)
Requires-Dist: grpcio (>=1.52.0)
Requires-Dist: more-itertools (>=10.2.0,<11.0.0)
Requires-Dist: pycryptodome (>=3.9.8,<4.0) ; extra == "cdr"
Requires-Dist: python-dotenv (==1.0)
Requires-Dist: requests (>=2.30,!=2.32.0,!=2.32.1) ; extra == "cdr"
Requires-Dist: urllib3 (!=2.2.0,!=2.2.1)
Project-URL: Documentation, https://docs.pachyderm.com/latest/sdk/python/
Project-URL: Repository, https://github.com/pachyderm/pachyderm/tree/master/python-sdk
